[
  {
    "topicId": "work",
    "topicNameVi": "Công việc",
    "cefrLevel": "B2",
    "words": [
      { "word": "career", "pos": "n.", "meaningVi": "sự nghiệp", "exampleSentence": "She built a successful ___ in medicine.", "iconHint": "ladder climbing toward a star" },
      { "word": "interview", "pos": "n.", "meaningVi": "buổi phỏng vấn", "exampleSentence": "I have a job ___ tomorrow.", "iconHint": "two people talking across a desk" },
      { "word": "job", "pos": "n.", "meaningVi": "công việc", "exampleSentence": "He got a new ___ at the hospital.", "iconHint": "briefcase" },
      { "word": "meeting", "pos": "n.", "meaningVi": "cuộc họp", "exampleSentence": "The ___ starts at 9 a.m.", "iconHint": "people around a conference table" },
      { "word": "office", "pos": "n.", "meaningVi": "văn phòng", "exampleSentence": "She works in a busy ___.", "iconHint": "office building with desks" },
      { "word": "skill", "pos": "n.", "meaningVi": "kỹ năng", "exampleSentence": "Communication is an important ___.", "iconHint": "gear with a checkmark" },
      { "word": "business", "pos": "n.", "meaningVi": "kinh doanh, doanh nghiệp", "exampleSentence": "He started his own ___ last year.", "iconHint": "storefront with a growth chart" },
      { "word": "company", "pos": "n.", "meaningVi": "công ty", "exampleSentence": "The ___ hired 50 new employees.", "iconHint": "office skyscraper" },
      { "word": "colleague", "pos": "n.", "meaningVi": "đồng nghiệp", "exampleSentence": "My ___ helped me finish the report.", "iconHint": "two coworkers shaking hands" },
      { "word": "employee", "pos": "n.", "meaningVi": "nhân viên", "exampleSentence": "Every ___ gets health insurance.", "iconHint": "person with an ID badge" },
      { "word": "employer", "pos": "n.", "meaningVi": "người sử dụng lao động, chủ", "exampleSentence": "Her ___ gave her a bonus.", "iconHint": "person behind an office desk" },
      { "word": "manager", "pos": "n.", "meaningVi": "quản lý", "exampleSentence": "The ___ approved my vacation request.", "iconHint": "person with a clipboard directing a team" },
      { "word": "salary", "pos": "n.", "meaningVi": "lương", "exampleSentence": "He negotiated a higher ___.", "iconHint": "stack of money with a paycheck" },
      { "word": "deadline", "pos": "n.", "meaningVi": "hạn chót", "exampleSentence": "The report ___ is next Monday.", "iconHint": "calendar with a red circle" },
      { "word": "negotiate", "pos": "v.", "meaningVi": "đàm phán, thương lượng", "exampleSentence": "They will ___ the contract terms tomorrow.", "iconHint": "two hands shaking over a table" },
      { "word": "promotion", "pos": "n.", "meaningVi": "sự thăng chức", "exampleSentence": "She earned a ___ after two years.", "iconHint": "arrow pointing up a career ladder" },
      { "word": "recruit", "pos": "v.", "meaningVi": "tuyển dụng", "exampleSentence": "The company plans to ___ ten engineers.", "iconHint": "magnifying glass over a resume" },
      { "word": "resign", "pos": "v.", "meaningVi": "từ chức", "exampleSentence": "He decided to ___ from his position.", "iconHint": "person walking out with a box" },
      { "word": "workplace", "pos": "n.", "meaningVi": "nơi làm việc", "exampleSentence": "Safety is important in every ___.", "iconHint": "office floor plan" }
    ]
  },
  {
    "topicId": "health",
    "topicNameVi": "Sức khỏe",
    "cefrLevel": "B2",
    "words": [
      { "word": "diet", "pos": "n.", "meaningVi": "chế độ ăn uống", "exampleSentence": "A balanced ___ keeps you healthy.", "iconHint": "plate divided into food groups" },
      { "word": "exercise", "pos": "n.", "meaningVi": "bài tập thể dục", "exampleSentence": "Regular ___ improves your mood.", "iconHint": "person jogging" },
      { "word": "disease", "pos": "n.", "meaningVi": "bệnh tật", "exampleSentence": "The vaccine protects against the ___.", "iconHint": "virus icon" },
      { "word": "headache", "pos": "n.", "meaningVi": "đau đầu", "exampleSentence": "I have a terrible ___ today.", "iconHint": "person holding their head in pain" },
      { "word": "illness", "pos": "n.", "meaningVi": "bệnh, tình trạng ốm", "exampleSentence": "She missed school due to ___.", "iconHint": "thermometer" },
      { "word": "injury", "pos": "n.", "meaningVi": "chấn thương", "exampleSentence": "He suffered a knee ___ during the match.", "iconHint": "bandaged knee" },
      { "word": "medicine", "pos": "n.", "meaningVi": "thuốc", "exampleSentence": "Take this ___ twice a day.", "iconHint": "pill bottle" },
      { "word": "pain", "pos": "n.", "meaningVi": "cơn đau", "exampleSentence": "The ___ in my back won't go away.", "iconHint": "highlighted sore back" },
      { "word": "patient", "pos": "n.", "meaningVi": "bệnh nhân", "exampleSentence": "The doctor examined the ___ carefully.", "iconHint": "person lying on a hospital bed" },
      { "word": "stress", "pos": "n.", "meaningVi": "căng thẳng", "exampleSentence": "Too much ___ can affect your sleep.", "iconHint": "tangled knot inside a head" },
      { "word": "symptom", "pos": "n.", "meaningVi": "triệu chứng", "exampleSentence": "Fever is a common ___ of the flu.", "iconHint": "clipboard with a checklist" },
      { "word": "treatment", "pos": "n.", "meaningVi": "phương pháp điều trị", "exampleSentence": "The ___ lasted six weeks.", "iconHint": "medical cross with a syringe" },
      { "word": "cure", "pos": "n.", "meaningVi": "phương thuốc chữa bệnh", "exampleSentence": "Scientists are searching for a ___.", "iconHint": "lab flask with a plus sign" },
      { "word": "infection", "pos": "n.", "meaningVi": "nhiễm trùng", "exampleSentence": "The wound got an ___.", "iconHint": "inflamed red skin" },
      { "word": "recover", "pos": "v.", "meaningVi": "hồi phục", "exampleSentence": "It took weeks to ___ from the flu.", "iconHint": "person standing up healthy again" },
      { "word": "surgery", "pos": "n.", "meaningVi": "phẫu thuật", "exampleSentence": "He needs ___ on his shoulder.", "iconHint": "surgical scalpel" },
      { "word": "therapy", "pos": "n.", "meaningVi": "liệu pháp trị liệu", "exampleSentence": "She goes to physical ___ twice a week.", "iconHint": "person stretching with a therapist" },
      { "word": "nutrition", "pos": "n.", "meaningVi": "dinh dưỡng", "exampleSentence": "Good ___ supports growth in children.", "iconHint": "basket of fruits and vegetables" }
    ]
  },
  {
    "topicId": "technology",
    "topicNameVi": "Công nghệ",
    "cefrLevel": "B2",
    "words": [
      { "word": "password", "pos": "n.", "meaningVi": "mật khẩu", "exampleSentence": "Never share your ___ with strangers.", "iconHint": "padlock with a key" },
      { "word": "browser", "pos": "n.", "meaningVi": "trình duyệt", "exampleSentence": "Open your ___ to visit the website.", "iconHint": "web browser window" },
      { "word": "hardware", "pos": "n.", "meaningVi": "phần cứng", "exampleSentence": "The computer's ___ needs an upgrade.", "iconHint": "computer tower with a screwdriver" },
      { "word": "battery", "pos": "n.", "meaningVi": "pin", "exampleSentence": "My phone's ___ is almost dead.", "iconHint": "battery level icon" },
      { "word": "software", "pos": "n.", "meaningVi": "phần mềm", "exampleSentence": "This ___ helps you edit photos.", "iconHint": "disk/CD icon" },
      { "word": "update", "pos": "v.", "meaningVi": "cập nhật", "exampleSentence": "Please ___ the app to the latest version.", "iconHint": "refresh arrow icon" },
      { "word": "artificial", "pos": "adj.", "meaningVi": "nhân tạo", "exampleSentence": "The chatbot uses ___ intelligence.", "iconHint": "robot head icon" },
      { "word": "install", "pos": "v.", "meaningVi": "cài đặt", "exampleSentence": "___ the program before you restart.", "iconHint": "download arrow into a box" },
      { "word": "virtual", "pos": "adj.", "meaningVi": "ảo (trên mạng)", "exampleSentence": "We had a ___ meeting on Zoom.", "iconHint": "VR headset" },
      { "word": "network", "pos": "n.", "meaningVi": "mạng lưới", "exampleSentence": "Connect to the office ___ first.", "iconHint": "connected wifi nodes" },
      { "word": "device", "pos": "n.", "meaningVi": "thiết bị", "exampleSentence": "This ___ can track your heart rate.", "iconHint": "smartwatch" },
      { "word": "digital", "pos": "adj.", "meaningVi": "kỹ thuật số", "exampleSentence": "We switched to ___ payments.", "iconHint": "digital screen with numbers" },
      { "word": "download", "pos": "v.", "meaningVi": "tải xuống", "exampleSentence": "___ the file before you open it.", "iconHint": "download arrow" },
      { "word": "data", "pos": "n.", "meaningVi": "dữ liệu", "exampleSentence": "The app collects a lot of ___.", "iconHint": "database cylinder icon" },
      { "word": "technology", "pos": "n.", "meaningVi": "công nghệ", "exampleSentence": "New ___ changes how we work.", "iconHint": "circuit board" },
      { "word": "screen", "pos": "n.", "meaningVi": "màn hình", "exampleSentence": "The ___ cracked when it fell.", "iconHint": "cracked phone screen" },
      { "word": "app", "pos": "n.", "meaningVi": "ứng dụng", "exampleSentence": "I downloaded a new fitness ___.", "iconHint": "grid of app icons" },
      { "word": "website", "pos": "n.", "meaningVi": "trang web", "exampleSentence": "Visit our ___ for more information.", "iconHint": "browser window with a globe" }
    ]
  },
  {
    "topicId": "adjectives",
    "topicNameVi": "Tính từ mô tả",
    "cefrLevel": "B2",
    "words": [
      { "word": "ambitious", "pos": "adj.", "meaningVi": "có tham vọng", "exampleSentence": "She is ___ and wants to become CEO.", "iconHint": "person climbing toward a flag on a mountain" },
      { "word": "calm", "pos": "adj.", "meaningVi": "bình tĩnh", "exampleSentence": "He stayed ___ during the emergency.", "iconHint": "person meditating peacefully" },
      { "word": "confident", "pos": "adj.", "meaningVi": "tự tin", "exampleSentence": "She gave a ___ presentation.", "iconHint": "person standing tall with a raised chin" },
      { "word": "generous", "pos": "adj.", "meaningVi": "hào phóng", "exampleSentence": "He is very ___ with his time.", "iconHint": "hand giving a gift" },
      { "word": "honest", "pos": "adj.", "meaningVi": "trung thực", "exampleSentence": "Please give me an ___ opinion.", "iconHint": "speech bubble with a checkmark" },
      { "word": "reliable", "pos": "adj.", "meaningVi": "đáng tin cậy", "exampleSentence": "She is a ___ colleague who never misses deadlines.", "iconHint": "handshake with a shield" },
      { "word": "shy", "pos": "adj.", "meaningVi": "nhút nhát", "exampleSentence": "He was too ___ to speak in class.", "iconHint": "person hiding behind their hands" },
      { "word": "talented", "pos": "adj.", "meaningVi": "tài năng", "exampleSentence": "She's a ___ musician.", "iconHint": "star above a person playing an instrument" },
      { "word": "aggressive", "pos": "adj.", "meaningVi": "hung hăng", "exampleSentence": "The dog became ___ when strangers approached.", "iconHint": "growling animal face" },
      { "word": "efficient", "pos": "adj.", "meaningVi": "hiệu quả", "exampleSentence": "The new system is more ___ than the old one.", "iconHint": "gear with a fast-forward arrow" },
      { "word": "flexible", "pos": "adj.", "meaningVi": "linh hoạt", "exampleSentence": "My work schedule is quite ___.", "iconHint": "bendable rubber arrow" },
      { "word": "sensitive", "pos": "adj.", "meaningVi": "nhạy cảm", "exampleSentence": "He is ___ about criticism.", "iconHint": "heart with a small crack" },
      { "word": "curious", "pos": "adj.", "meaningVi": "tò mò", "exampleSentence": "The child was ___ about everything.", "iconHint": "magnifying glass over a question mark" },
      { "word": "optimistic", "pos": "adj.", "meaningVi": "lạc quan", "exampleSentence": "She stayed ___ despite the setback.", "iconHint": "sun rising over a hill" },
      { "word": "creative", "pos": "adj.", "meaningVi": "sáng tạo", "exampleSentence": "He came up with a ___ solution.", "iconHint": "lightbulb with a paint splash" },
      { "word": "nervous", "pos": "adj.", "meaningVi": "lo lắng, hồi hộp", "exampleSentence": "I felt ___ before the exam.", "iconHint": "person sweating with shaky hands" },
      { "word": "modest", "pos": "adj.", "meaningVi": "khiêm tốn", "exampleSentence": "Despite his success, he remained ___.", "iconHint": "person bowing slightly" },
      { "word": "precise", "pos": "adj.", "meaningVi": "chính xác", "exampleSentence": "Give me ___ instructions.", "iconHint": "target with an arrow in the bullseye" }
    ]
  }
]
